{
  "image_count": 13,
  "seo_title": "Electrolux EEM63310L 45 cm täisintegreeritav nõudepesumasin",
  "main_query": "Electrolux EEM63310L 45 cm integreeritav nõudepesumasin AirDry",
  "additional_queries": [
    "kuidas valida vaikne 45 cm integreeritav nõudepesumasin väikese köögi jaoks Electrolux EEM63310L",
    "45 cm nõudepesumasin 10 nõudekomplektile väikese pere jaoks Electrolux EEM63310L",
    "Electrolux EEM63310L vs teised 45 cm integreeritavad nõudepesumasinad võrdlus",
    "Electrolux EEM63310L paigaldus ja AirDry funktsiooniga nõudepesumasina kasutusjuhend"
  ],
  "updated": 13,
  "cycle_used": [
    "kuidas valida vaikne 45 cm integreeritav nõudepesumasin väikese köögi jaoks Electrolux EEM63310L",
    "45 cm nõudepesumasin 10 nõudekomplektile väikese pere jaoks Electrolux EEM63310L",
    "Electrolux EEM63310L vs teised 45 cm integreeritavad nõudepesumasinad võrdlus",
    "Electrolux EEM63310L paigaldus ja AirDry funktsiooniga nõudepesumasina kasutusjuhend",
    "kuidas valida vaikne 45 cm integreeritav nõudepesumasin väikese köögi jaoks Electrolux EEM63310L",
    "45 cm nõudepesumasin 10 nõudekomplektile väikese pere jaoks Electrolux EEM63310L",
    "Electrolux EEM63310L vs teised 45 cm integreeritavad nõudepesumasinad võrdlus",
    "Electrolux EEM63310L paigaldus ja AirDry funktsiooniga nõudepesumasina kasutusjuhend",
    "kuidas valida vaikne 45 cm integreeritav nõudepesumasin väikese köögi jaoks Electrolux EEM63310L",
    "45 cm nõudepesumasin 10 nõudekomplektile väikese pere jaoks Electrolux EEM63310L"
  ],
  "description_applied": "45 cm täisintegreeritav Electrolux EEM63310L mahutab kuni 10 nõudekomplekti ja sobib hästi väiksemale köögile. Vaikne töö (44 dB), ECO-veekulu 9,9 l, AirDry ukse automaatne avamine ning kolm korvi puutetundliku LCD-juhtimisega tagavad ökonoomse ja mugava kasutuse."
}