{
  "image_count": 18,
  "seo_title": "Samsung BRB80F30ADF0EO integreeritav No Frost külmik",
  "main_query": "integreeritav külmik Samsung BRB80F30ADF0EO Twin Cooling No Frost",
  "additional_queries": [
    "kuidas hoida toit kauem värskena integreeritava külmikuga Samsung BRB80F30ADF0EO Twin Cooling",
    "integreeritav No Frost külmik 60 cm alumise sügavkülmaga ja Wi-Fi Samsung SmartThings jaoks",
    "millega erineb Samsung BRB80F30ADF0EO teistest integreeritavatest külmikutest Twin Cooling ja Cool Select+ tsooniga",
    "kuidas seadistada ja kasutada SmartThings AI energiarežiimi külmikul Samsung BRB80F30ADF0EO"
  ],
  "updated": 18,
  "cycle_used": [
    "kuidas hoida toit kauem värskena integreeritava külmikuga Samsung BRB80F30ADF0EO Twin Cooling",
    "integreeritav No Frost külmik 60 cm alumise sügavkülmaga ja Wi-Fi Samsung SmartThings jaoks",
    "millega erineb Samsung BRB80F30ADF0EO teistest integreeritavatest külmikutest Twin Cooling ja Cool Select+ tsooniga",
    "kuidas seadistada ja kasutada SmartThings AI energiarežiimi külmikul Samsung BRB80F30ADF0EO",
    "kuidas hoida toit kauem värskena integreeritava külmikuga Samsung BRB80F30ADF0EO Twin Cooling",
    "integreeritav No Frost külmik 60 cm alumise sügavkülmaga ja Wi-Fi Samsung SmartThings jaoks",
    "millega erineb Samsung BRB80F30ADF0EO teistest integreeritavatest külmikutest Twin Cooling ja Cool Select+ tsooniga",
    "kuidas seadistada ja kasutada SmartThings AI energiarežiimi külmikul Samsung BRB80F30ADF0EO",
    "kuidas hoida toit kauem värskena integreeritava külmikuga Samsung BRB80F30ADF0EO Twin Cooling",
    "integreeritav No Frost külmik 60 cm alumise sügavkülmaga ja Wi-Fi Samsung SmartThings jaoks",
    "millega erineb Samsung BRB80F30ADF0EO teistest integreeritavatest külmikutest Twin Cooling ja Cool Select+ tsooniga",
    "kuidas seadistada ja kasutada SmartThings AI energiarežiimi külmikul Samsung BRB80F30ADF0EO",
    "kuidas hoida toit kauem värskena integreeritava külmikuga Samsung BRB80F30ADF0EO Twin Cooling",
    "integreeritav No Frost külmik 60 cm alumise sügavkülmaga ja Wi-Fi Samsung SmartThings jaoks",
    "millega erineb Samsung BRB80F30ADF0EO teistest integreeritavatest külmikutest Twin Cooling ja Cool Select+ tsooniga"
  ],
  "description_applied": "Integreeritav külmik alumise sügavkülmaga sobib 60 cm köögimööbli avasse ja pakub 224 l külmiku ning 74 l sügavkülma mahtu. Twin Cooling ja Cool Select+ tsoon hoiavad toidu kauem värskena ja annavad paindlikud säilitustingimused. No Frost tehnoloogia ja Wi‑Fi kaudu juhitav AI energiarežiim lihtsustavad hooldust ja energiakulu jälgimist."
}