{
  "name": "ENP7TD75S",
  "type": "simple",
  "status": "publish",
  "catalog_visibility": "visible",
  "description": "<a class=\"flix-minisite-button\" title=\"Flixmedia Minisite\" href=\"javascript:;\" onclick=\"FlixServices.flixminisite.msOpenWin(&quot;https://media.flixcar.com/modular/static/minisite/show.html?lang=en&amp;prodid=2340479&amp;mpn=ENP7TD75S&amp;ean=7333394008219&amp;distid=15151&amp;flIso=lt&amp;appc=d2ViLWFwaS9lbi8xNTE1MS9FTlA3VEQ3NVM3MzMzMzk0MDA4MjE5WlM1d2NtVnVkR0V1YkhRL3QuanNvbj9tcG49RU5QN1RENzVTJmVhbj03MzMzMzk0MDA4MjE5JmRpc3RJZD0xNTE1MSZpc289ZW4mZmxJc289bHQ=&quot;);\"><img style=\"height:auto;width:auto;\" height=\"100\" width=\"100\" id=\"_flixbtn2340479\" alt=\"Minisite button image\" border=\"0\" src=\"//media.flixcar.com/modular/flix-button/?env=prod&amp;switch=main&amp;manuId=1307&amp;isoCode=lt&amp;prodId=2340479&amp;template=electrolux-major/electrolux&amp;distId=?&amp;distId=15151\"></a>",
  "description_original": "",
  "description_flix": "<a class=\"flix-minisite-button\" title=\"Flixmedia Minisite\" href=\"javascript:;\" onclick=\"FlixServices.flixminisite.msOpenWin(&quot;https://media.flixcar.com/modular/static/minisite/show.html?lang=en&amp;prodid=2340479&amp;mpn=ENP7TD75S&amp;ean=7333394008219&amp;distid=15151&amp;flIso=lt&amp;appc=d2ViLWFwaS9lbi8xNTE1MS9FTlA3VEQ3NVM3MzMzMzk0MDA4MjE5WlM1d2NtVnVkR0V1YkhRL3QuanNvbj9tcG49RU5QN1RENzVTJmVhbj03MzMzMzk0MDA4MjE5JmRpc3RJZD0xNTE1MSZpc289ZW4mZmxJc289bHQ=&quot;);\"><img style=\"height:auto;width:auto;\" height=\"100\" width=\"100\" id=\"_flixbtn2340479\" alt=\"Minisite button image\" border=\"0\" src=\"//media.flixcar.com/modular/flix-button/?env=prod&amp;switch=main&amp;manuId=1307&amp;isoCode=lt&amp;prodId=2340479&amp;template=electrolux-major/electrolux&amp;distId=?&amp;distId=15151\"></a>",
  "short_description": "",
  "sku": "ENP7TD75S",
  "regular_price": "1459.00",
  "sale_price": "",
  "tax_status": "taxable",
  "tax_class": "",
  "manage_stock": true,
  "stock_quantity": 5,
  "backorders": "no",
  "backorders_allowed": false,
  "backordered": false,
  "supplier_sku_prefix": "PR",
  "weight": "83.00",
  "dimensions": {
    "length": "",
    "width": "",
    "height": ""
  },
  "shipping_required": true,
  "shipping_taxable": true,
  "shipping_class": "prenta",
  "reviews_allowed": true,
  "categories": [
    {
      "name": "Kodutehnika > Integreeritav kodutehnika > Integreeritavad külmikud",
      "slug": "kodutehnika-integreeritav-kodutehnika-integreeritavad-klmikud"
    }
  ],
  "brands": [
    {
      "name": "ELECTROLUX",
      "slug": "electrolux"
    }
  ],
  "tags": [],
  "images": [
    {
      "src": "https://e.prenta.lt/web/image/product.product/30964/image?unique=67b8c1e",
      "position": 0,
      "alt": "ENP7TD75S"
    }
  ],
  "meta_data": [
    {
      "key": "_bp_gtin13",
      "value": "7333394008219"
    },
    {
      "key": "_bp_supplier",
      "value": "Prenta"
    },
    {
      "key": "_bp_brand",
      "value": "ELECTROLUX"
    }
  ],
  "attributes": [
    {
      "name": "Producer",
      "visible": true,
      "variation": false,
      "options": [
        "Electrolux"
      ]
    },
    {
      "name": "Type of installation",
      "visible": true,
      "variation": false,
      "options": [
        "Built in"
      ]
    },
    {
      "name": "Type",
      "visible": true,
      "variation": false,
      "options": [
        "Fridge with bottom freezer"
      ]
    },
    {
      "name": "Type of refrigeration technology",
      "visible": true,
      "variation": false,
      "options": [
        "No frost"
      ]
    },
    {
      "name": "Height",
      "visible": true,
      "variation": false,
      "options": [
        "188.4"
      ]
    },
    {
      "name": "Width",
      "visible": true,
      "variation": false,
      "options": [
        "69.6"
      ]
    },
    {
      "name": "Depth",
      "visible": true,
      "variation": false,
      "options": [
        "54.9"
      ]
    },
    {
      "name": " Color",
      "visible": true,
      "variation": false,
      "options": [
        "White"
      ]
    },
    {
      "name": "New Energy efficiency class",
      "visible": true,
      "variation": false,
      "options": [
        "D"
      ]
    },
    {
      "name": "Cold drawer",
      "visible": true,
      "variation": false,
      "options": [
        "No"
      ]
    },
    {
      "name": "Freezer to fridge",
      "visible": true,
      "variation": false,
      "options": [
        "No"
      ]
    },
    {
      "name": "Control",
      "visible": true,
      "variation": false,
      "options": [
        "Touch control with LCD"
      ]
    },
    {
      "name": "Annual energy consumption",
      "visible": true,
      "variation": false,
      "options": [
        "197"
      ]
    },
    {
      "name": "Net capacity of refrigerator",
      "visible": true,
      "variation": false,
      "options": [
        "287"
      ]
    },
    {
      "name": "Net capacity of freezer",
      "visible": true,
      "variation": false,
      "options": [
        "89"
      ]
    },
    {
      "name": "Type of hinges",
      "visible": true,
      "variation": false,
      "options": [
        "Sliding"
      ]
    },
    {
      "name": "Soft door closing",
      "visible": true,
      "variation": false,
      "options": [
        "No"
      ]
    },
    {
      "name": "Metallized rear wall",
      "visible": true,
      "variation": false,
      "options": [
        "No"
      ]
    },
    {
      "name": "Door handle",
      "visible": true,
      "variation": false,
      "options": [
        "No"
      ]
    },
    {
      "name": "Humidity controlled drawer for fruits/vegetables",
      "visible": true,
      "variation": false,
      "options": [
        "Yes"
      ]
    },
    {
      "name": "Ice maker",
      "visible": true,
      "variation": false,
      "options": [
        "No"
      ]
    },
    {
      "name": "Type of compressor",
      "visible": true,
      "variation": false,
      "options": [
        "Inverter"
      ]
    },
    {
      "name": "Fan",
      "visible": true,
      "variation": false,
      "options": [
        "Yes"
      ]
    },
    {
      "name": "Air cleaning filter",
      "visible": true,
      "variation": false,
      "options": [
        "Yes"
      ]
    },
    {
      "name": "Bottle shelf",
      "visible": true,
      "variation": false,
      "options": [
        "No"
      ]
    },
    {
      "name": "Divisible glass shelf",
      "visible": true,
      "variation": false,
      "options": [
        "No"
      ]
    },
    {
      "name": "Door lock ",
      "visible": true,
      "variation": false,
      "options": [
        "No"
      ]
    },
    {
      "name": "Open door signal",
      "visible": true,
      "variation": false,
      "options": [
        "Yes"
      ]
    },
    {
      "name": "Rising temperature indicator",
      "visible": true,
      "variation": false,
      "options": [
        "Yes"
      ]
    },
    {
      "name": " Eco mode",
      "visible": true,
      "variation": false,
      "options": [
        "Yes"
      ]
    },
    {
      "name": "Holiday function",
      "visible": true,
      "variation": false,
      "options": [
        "No"
      ]
    },
    {
      "name": "Individually adjustable door shelves",
      "visible": true,
      "variation": false,
      "options": [
        "No"
      ]
    },
    {
      "name": "Rapid cooling in refrigerator",
      "visible": true,
      "variation": false,
      "options": [
        "Yes"
      ]
    },
    {
      "name": "Reversible doors",
      "visible": true,
      "variation": false,
      "options": [
        "Yes"
      ]
    },
    {
      "name": "Lighting",
      "visible": true,
      "variation": false,
      "options": [
        "LED"
      ]
    },
    {
      "name": "Fully removable drawers and intermediate glass shelves in freezer",
      "visible": true,
      "variation": false,
      "options": [
        "No"
      ]
    },
    {
      "name": "Freezer freezing temperature",
      "visible": true,
      "variation": false,
      "options": [
        "-15°C - -26°C"
      ]
    },
    {
      "name": "Fast freeze function in freezer",
      "visible": true,
      "variation": false,
      "options": [
        "Yes"
      ]
    },
    {
      "name": "Maximum freezer storage time in power failure",
      "visible": true,
      "variation": false,
      "options": [
        "12"
      ]
    },
    {
      "name": "Noise level",
      "visible": true,
      "variation": false,
      "options": [
        "35"
      ]
    },
    {
      "name": "Noise level class",
      "visible": true,
      "variation": false,
      "options": [
        "B"
      ]
    },
    {
      "name": "Standardized height",
      "visible": true,
      "variation": false,
      "options": [
        "190"
      ]
    },
    {
      "name": "Standardized width",
      "visible": true,
      "variation": false,
      "options": [
        "70.0"
      ]
    },
    {
      "name": "Wi-Fi",
      "visible": true,
      "variation": false,
      "options": [
        "Yes"
      ]
    },
    {
      "name": "Lightning",
      "visible": true,
      "variation": false,
      "options": [
        "LED"
      ]
    },
    {
      "name": "Freezing capacity in 24 hours",
      "visible": true,
      "variation": false,
      "options": [
        "11.5"
      ]
    },
    {
      "name": "Number of freezer boxes/shelfs",
      "visible": true,
      "variation": false,
      "options": [
        "3"
      ]
    },
    {
      "name": "Energy efficiency class",
      "visible": true,
      "variation": false,
      "options": [
        "D"
      ]
    }
  ],
  "source": {
    "prenta_product_id": 30964,
    "prenta_category_path": "All > Saleable > Home appliances > Built in > Fridge",
    "prenta_category_id": 27
  }
}