{
  "image_count": 16,
  "seo_title": "AEG TB6SM171DB integreeritav mikrolaineahi SteamSet",
  "main_query": "AEG TB6SM171DB integreeritav aurufunktsiooniga mikrolaineahi",
  "additional_queries": [
    "kuidas leida madalasse seinakappi sobiv ainult 30 cm sügavune integreeritav mikrolaineahi",
    "integreeritav 17 l 800 W mikrolaineahi aurufunktsiooniga väikesele köögile",
    "AEG TB6SM171DB võrdlus teiste integreeritavate mikrolaineahjudega",
    "kuidas kasutada ja puhastada AEG TB6SM171DB integreeritavat mikrolaineahju aurufunktsiooniga"
  ],
  "updated": 16,
  "cycle_used": [
    "kuidas leida madalasse seinakappi sobiv ainult 30 cm sügavune integreeritav mikrolaineahi",
    "integreeritav 17 l 800 W mikrolaineahi aurufunktsiooniga väikesele köögile",
    "AEG TB6SM171DB võrdlus teiste integreeritavate mikrolaineahjudega",
    "kuidas kasutada ja puhastada AEG TB6SM171DB integreeritavat mikrolaineahju aurufunktsiooniga",
    "kuidas leida madalasse seinakappi sobiv ainult 30 cm sügavune integreeritav mikrolaineahi",
    "integreeritav 17 l 800 W mikrolaineahi aurufunktsiooniga väikesele köögile",
    "AEG TB6SM171DB võrdlus teiste integreeritavate mikrolaineahjudega",
    "kuidas kasutada ja puhastada AEG TB6SM171DB integreeritavat mikrolaineahju aurufunktsiooniga",
    "kuidas leida madalasse seinakappi sobiv ainult 30 cm sügavune integreeritav mikrolaineahi",
    "integreeritav 17 l 800 W mikrolaineahi aurufunktsiooniga väikesele köögile",
    "AEG TB6SM171DB võrdlus teiste integreeritavate mikrolaineahjudega",
    "kuidas kasutada ja puhastada AEG TB6SM171DB integreeritavat mikrolaineahju aurufunktsiooniga",
    "kuidas leida madalasse seinakappi sobiv ainult 30 cm sügavune integreeritav mikrolaineahi"
  ],
  "description_applied": "17 L integreeritav mikrolaineahi sobib paigalduseks 36 x 56,2 x 30 cm köögimööbli avasse ja ka kitsamatesse seinakappidesse. SteamSet aurufunktsioon, automaatsed küpsetus- ja sulatusprogrammid, 30 s kiire käivitus ning lapselukk teevad igapäevase kasutamise mugavaks ja turvaliseks."
}