{
  "image_count": 9,
  "seo_title": "AEG FSE73527P 45 cm integreeritav nõudepesumasin",
  "main_query": "AEG FSE73527P 45 cm integreeritav nõudepesumasin SatelliteClean ja MaxiFlexiga",
  "additional_queries": [
    "kuidas pesta õrnu veiniklaase nõudepesumasinas AEG FSE73527P SoftGrip ja SoftSpikes hoidikutega",
    "45 cm integreeritav nõudepesumasin 10 nõudekomplektile väikesele köögile AEG FSE73527P",
    "millega erineb AEG FSE73527P teistest 45 cm AEG integreeritavatest nõudepesumasinatest",
    "kuidas kasutada QuickSelect juhtpaneeli ja SatelliteClean funktsiooni AEG FSE73527P nõudepesumasinal"
  ],
  "updated": 9,
  "cycle_used": [
    "kuidas pesta õrnu veiniklaase nõudepesumasinas AEG FSE73527P SoftGrip ja SoftSpikes hoidikutega",
    "45 cm integreeritav nõudepesumasin 10 nõudekomplektile väikesele köögile AEG FSE73527P",
    "millega erineb AEG FSE73527P teistest 45 cm AEG integreeritavatest nõudepesumasinatest",
    "kuidas kasutada QuickSelect juhtpaneeli ja SatelliteClean funktsiooni AEG FSE73527P nõudepesumasinal",
    "kuidas pesta õrnu veiniklaase nõudepesumasinas AEG FSE73527P SoftGrip ja SoftSpikes hoidikutega",
    "45 cm integreeritav nõudepesumasin 10 nõudekomplektile väikesele köögile AEG FSE73527P"
  ],
  "description_applied": "45 cm lai AEG FSE73527P integreeritav nõudepesumasin mahutab 10 nõudekomplekti ja sobib väiksemale leibkonnale. SoftGrip ja SoftSpikes kaitsevad õrnu klaase, MaxiFlex sahtel hoiab eri kujuga söögiriistu. SatelliteClean pihustid, QuickSelect puutejuhtimine ja automaatne ukse avanemine tagavad põhjaliku ja säästliku pesu."
}