{
  "image_count": 1,
  "seo_title": "Gorenje GV520E10S 45 cm integreeritav nõudepesumasin",
  "main_query": "Gorenje GV520E10S 45 cm integreeritav nõudepesumasin 11 komplektile",
  "additional_queries": [
    "kuidas lahendada väikese köögi nõudepesu 45 cm integreeritava nõudepesumasinaga Gorenje GV520E10S",
    "45 cm integreeritav nõudepesumasin 11 nõudekomplektiga väiksesse kööki",
    "Gorenje GV520E10S võrdlus teiste 45 cm integreeritavate nõudepesumasinatega",
    "kuidas paigaldada ja kasutada Gorenje GV520E10S integreeritavat nõudepesumasinat"
  ],
  "updated": 1,
  "cycle_used": [],
  "description_applied": "45 cm täisintegreeritav nõudepesumasin mahutab 11 nõudekomplekti ja sobib väiksemasse kööki. 5 programmi, 3 temperatuuri, HalfLoad ja aja kokkuhoiu funktsioon kohandavad pesu vastavalt täituvusele, veekulu on u 9,5 l tsükli kohta. Roostevabast terasest sisemus, invertermootor ja AquaStop lekkevastane kaitse suurendavad töökindlust."
}